LICENSE
typedmonarchmoney/__init__.py
typedmonarchmoney/icon.py
typedmonarchmoney/models.py
typedmonarchmoney/monarchmoney_typed.py
typedmonarchmoney/py.typed
typedmonarchmoney-0.4.4.dist-info/LICENSE
typedmonarchmoney-0.4.4.dist-info/METADATA
typedmonarchmoney-0.4.4.dist-info/WHEEL
typedmonarchmoney-0.4.4.dist-info/RECORD
