Metadata-Version: 2.1
Name: typedmonarchmoney
Version: 0.4.4
Summary: A Typed wrapper around Monarch Money
License: MIT
Author: Jeff Stein
Author-email: jeffstein@gmail.com
Requires-Python: >=3.12,<4.0
Classifier: License :: OSI Approved :: MIT License
Classifier: Programming Language :: Python :: 3
Classifier: Programming Language :: Python :: 3.12
Requires-Dist: monarchmoney (>=0.1.13,<0.2.0)
Requires-Dist: rich (>=10.1.0)
